LICENSE
README.md
setup.py
cgai_socket/__init__.py
cgai_socket/cgai_client.py
cgai_socket/cgai_server.py
cgai_socket.egg-info/PKG-INFO
cgai_socket.egg-info/SOURCES.txt
cgai_socket.egg-info/dependency_links.txt
cgai_socket.egg-info/top_level.txt