Metadata-Version: 2.1
Name: cgai-socket
Version: 0.0.8
Summary: A simple and fast library supporting custom callback function.
Home-page: https://github.com/zxzxde/cgai-socket
Author: Master Zhang
Author-email: 360014296@qq.com
License: UNKNOWN
Platform: UNKNOWN
Classifier: License :: OSI Approved :: GNU General Public License v3 (GPLv3)
Classifier: Operating System :: OS Independent
Classifier: Programming Language :: Python :: 2.7
Classifier: Programming Language :: Python :: 3
Classifier: Programming Language :: Python :: 3.5
Classifier: Programming Language :: Python :: 3.6
Classifier: Programming Language :: Python :: 3.7
Classifier: Programming Language :: Python :: 3.8
Classifier: Programming Language :: Python :: 3.9
License-File: LICENSE
